julien_python_toolkit/__init__.py
julien_python_toolkit/email_logger.py
julien_python_toolkit/email_sender.py
julien_python_toolkit/file_utilities.py
julien_python_toolkit/google_services.py
julien_python_toolkit/log_utilities.py
julien_python_toolkit-0.2.1.dist-info/LICENSE.txt
julien_python_toolkit-0.2.1.dist-info/METADATA
julien_python_toolkit-0.2.1.dist-info/WHEEL
julien_python_toolkit-0.2.1.dist-info/top_level.txt
julien_python_toolkit-0.2.1.dist-info/RECORD
