Metadata-Version: 2.1
Name: julien-python-toolkit
Version: 0.2.1
Summary: Important code that I reuse through multiple projects. Please see license for allowed use.
Home-page: https://github.com/JulienPython/JulienPythonToolkit-V001
Author: Julien Python
Author-email: python.julien@hotmail.com
License: Custom Non-Commercial License
Classifier: Programming Language :: Python :: 3
License-File: LICENSE.txt
Requires-Dist: certifi==2024.8.30
Requires-Dist: google-api-core==2.19.1
Requires-Dist: google-api-python-client==2.139.0
Requires-Dist: google-auth==2.32.0
Requires-Dist: google-auth-httplib2==0.2.0
Requires-Dist: google-auth-oauthlib==1.2.1
Requires-Dist: googleapis-common-protos==1.63.2
